VASSAL-stubs/__init__.pyi
VASSAL-stubs/build/__init__.pyi
VASSAL-stubs/build/module/__init__.pyi
VASSAL-stubs/build/module/chessclockcontrol/__init__.pyi
VASSAL-stubs/build/module/dice/__init__.pyi
VASSAL-stubs/build/module/documentation/__init__.pyi
VASSAL-stubs/build/module/folder/__init__.pyi
VASSAL-stubs/build/module/gamepieceimage/__init__.pyi
VASSAL-stubs/build/module/map/__init__.pyi
VASSAL-stubs/build/module/map/boardPicker/__init__.pyi
VASSAL-stubs/build/module/map/boardPicker/board/__init__.pyi
VASSAL-stubs/build/module/map/boardPicker/board/mapgrid/__init__.pyi
VASSAL-stubs/build/module/map/deck/__init__.pyi
VASSAL-stubs/build/module/metadata/__init__.pyi
VASSAL-stubs/build/module/noteswindow/__init__.pyi
VASSAL-stubs/build/module/properties/__init__.pyi
VASSAL-stubs/build/module/turn/__init__.pyi
VASSAL-stubs/build/widget/__init__.pyi
VASSAL-stubs/chat/__init__.pyi
VASSAL-stubs/chat/messageboard/__init__.pyi
VASSAL-stubs/chat/node/__init__.pyi
VASSAL-stubs/chat/peer2peer/__init__.pyi
VASSAL-stubs/chat/ui/__init__.pyi
VASSAL-stubs/command/__init__.pyi
VASSAL-stubs/configure/__init__.pyi
VASSAL-stubs/configure/password/__init__.pyi
VASSAL-stubs/counters/__init__.pyi
VASSAL-stubs/i18n/__init__.pyi
VASSAL-stubs/launch/__init__.pyi
VASSAL-stubs/preferences/__init__.pyi
VASSAL-stubs/property/__init__.pyi
VASSAL-stubs/script/__init__.pyi
VASSAL-stubs/script/expression/__init__.pyi
VASSAL-stubs/script/proxy/__init__.pyi
VASSAL-stubs/search/__init__.pyi
VASSAL-stubs/tools/__init__.pyi
VASSAL-stubs/tools/bug/__init__.pyi
VASSAL-stubs/tools/concurrent/__init__.pyi
VASSAL-stubs/tools/concurrent/listener/__init__.pyi
VASSAL-stubs/tools/deprecation/__init__.pyi
VASSAL-stubs/tools/filechooser/__init__.pyi
VASSAL-stubs/tools/icon/__init__.pyi
VASSAL-stubs/tools/image/__init__.pyi
VASSAL-stubs/tools/image/svg/__init__.pyi
VASSAL-stubs/tools/image/tilecache/__init__.pyi
VASSAL-stubs/tools/imageop/__init__.pyi
VASSAL-stubs/tools/imports/__init__.pyi
vassal_python-0.4.3.dist-info/LICENSE.txt
vassal_python-0.4.3.dist-info/METADATA
vassal_python-0.4.3.dist-info/WHEEL
vassal_python-0.4.3.dist-info/top_level.txt
vassal_python-0.4.3.dist-info/RECORD
