Metadata-Version: 2.1
Name: vassal-python
Version: 0.4.3
Summary: Python tools for manipulating VASSAL modules
Home-page: https://github.com/jasonestewart/vassal-python
Author: Jason E. Stewart
Author-email: jason.e.stewart@gmail.com
Project-URL: Bug Reports, https://github.com/jasonestewart/vassal-python/issues
Project-URL: Say Thanks!, https://saythanks.io/to/jasonestewart
Project-URL: Source, https://github.com/jasonestewart/vassal-python/
Keywords: VASSAL module development
Classifier: Development Status :: 3 - Alpha
Classifier: Intended Audience :: Developers
Classifier: Topic :: Games/Entertainment
Classifier: Topic :: Software Development :: Libraries :: Java Libraries
Classifier: License :: OSI Approved :: GNU Lesser General Public License v2 or later (LGPLv2+)
Classifier: Programming Language :: Python :: 3.10
Classifier: Programming Language :: Python :: 3 :: Only
Requires-Python: >=3.7, <4
License-File: LICENSE.txt
Requires-Dist: jpype1 (<2.*,>=1.2.1)
Requires-Dist: numpy
Requires-Dist: pillow
Requires-Dist: opencv-python
Requires-Dist: pytesseract
